datasette_tiddlywiki/__init__.py
datasette_tiddlywiki/tiddlywiki.html
datasette_tiddlywiki-0.2.dist-info/LICENSE
datasette_tiddlywiki-0.2.dist-info/METADATA
datasette_tiddlywiki-0.2.dist-info/WHEEL
datasette_tiddlywiki-0.2.dist-info/entry_points.txt
datasette_tiddlywiki-0.2.dist-info/top_level.txt
datasette_tiddlywiki-0.2.dist-info/RECORD
