Metadata-Version: 2.1
Name: datasette-tiddlywiki
Version: 0.2
Summary: Run TiddlyWiki in Datasette and save Tiddlers to a SQLite database
Home-page: https://github.com/simonw/datasette-tiddlywiki
Author: Simon Willison
License: Apache License, Version 2.0
Project-URL: Issues, https://github.com/simonw/datasette-tiddlywiki/issues
Project-URL: CI, https://github.com/simonw/datasette-tiddlywiki/actions
Project-URL: Changelog, https://github.com/simonw/datasette-tiddlywiki/releases
Platform: UNKNOWN
Classifier: Framework :: Datasette
Classifier: License :: OSI Approved :: Apache Software License
Requires-Python: >=3.6
License-File: LICENSE
Requires-Dist: datasette
Provides-Extra: test
Requires-Dist: pytest ; extra == 'test'
Requires-Dist: pytest-asyncio ; extra == 'test'
